lifxlan/__init__.py
lifxlan/device.py
lifxlan/errors.py
lifxlan/generate_products_file.py
lifxlan/group.py
lifxlan/lifxlan.py
lifxlan/light.py
lifxlan/message.py
lifxlan/msgtypes.py
lifxlan/multizonelight.py
lifxlan/products.py
lifxlan/switch.py
lifxlan/tilechain.py
lifxlan/unpack.py
lifxlan/utils.py
lifxlan-1.2.9.dist-info/licenses/LICENSE.md
lifxlan-1.2.9.dist-info/METADATA
lifxlan-1.2.9.dist-info/WHEEL
lifxlan-1.2.9.dist-info/top_level.txt
lifxlan-1.2.9.dist-info/RECORD
