Metadata-Version: 2.4
Name: lifxlan
Version: 1.2.9
Summary: API for local communication with LIFX devices over a LAN.
Home-page: http://github.com/mclarkk/lifxlan
Author: Meghan Clark
Author-email: mclarkk@berkeley.edu
License: MIT
Classifier: License :: OSI Approved :: MIT License
Classifier: Programming Language :: Python :: 3
License-File: LICENSE.md
Requires-Dist: bitstring
Requires-Dist: ifaddr
Dynamic: author
Dynamic: author-email
Dynamic: classifier
Dynamic: home-page
Dynamic: license
Dynamic: license-file
Dynamic: requires-dist
Dynamic: summary
